README.md
README.rst
setup.py
stackdriver_error_reporting/__init__.py
stackdriver_error_reporting/error_logger.py
stackdriver_error_reporting.egg-info/PKG-INFO
stackdriver_error_reporting.egg-info/SOURCES.txt
stackdriver_error_reporting.egg-info/dependency_links.txt
stackdriver_error_reporting.egg-info/not-zip-safe
stackdriver_error_reporting.egg-info/top_level.txt