Metadata-Version: 1.0
Name: stackdriver-error-reporting
Version: 1.1.1
Summary: Reports errors to Stackdriver Error Reporting
Home-page: http://github.com/crowdynews/stackdriver-error-reporting-python
Author: Lennart Kloppenburg
Author-email: lennart@crowdynews.com
License: MIT
Platform: UNKNOWN
